[{"senderKeyId":119979188,"senderChainKey":{"iteration":493,"seed":"j9GCrqFIBdJLrPA7eo/ehGdtaBF5j/Hp80pvB8n/pwQ="},"senderSigningKey":{"public":"BY+uKtN0XxhHNGBwbM/FcDSksG/aab15yMPr3xvr86Rl"},"senderMessageKeys":[{},{},{},{},{},{},{},{},{},{},{},{},{},{},{},{},{},{},{},{},{},{},{},{},{},{},{},{},{},{},{},{},{},{},{},{},{},{},{},{},{},{},{},{},{},{},{},{},{},{},{},{},{},{},{},{},{},{},{},{},{},{},{},{},{},{},{},{},{},{},{},{},{},{},{},{},{},{},{},{},{},{},{},{},{},{},{},{},{},{},{},{},{},{},{},{},{},{},{},{},{},{},{},{},{},{},{},{},{},{},{},{},{},{},{},{},{},{},{},{},{},{},{},{},{},{},{},{},{},{},{},{},{},{},{},{},{},{},{},{},{},{},{},{},{},{},{},{},{},{},{},{},{},{},{},{},{},{},{},{},{},{},{},{},{},{},{},{},{},{},{},{},{},{},{},{},{},{},{},{},{},{},{},{},{},{},{},{},{},{},{},{},{},{},{},{},{},{},{},{},{},{},{},{},{},{},{},{},{},{},{},{},{},{},{},{},{},{},{},{},{},{},{},{},{},{},{},{},{},{},{},{},{},{},{},{},{},{},{},{},{},{},{},{},{},{},{},{},{},{},{},{},{},{},{},{},{},{},{},{},{},{},{},{},{},{},{},{},{},{},{},{},{},{},{},{},{},{},{},{},{},{},{},{},{},{},{},{},{},{},{},{},{},{},{},{},{},{},{},{},{},{},{},{},{},{},{},{},{},{},{},{},{},{},{},{},{},{},{},{},{},{},{},{},{},{},{},{},{},{},{},{},{},{},{},{},{},{},{},{},{},{},{}]},{"senderKeyId":119979188,"senderChainKey":{"iteration":5,"seed":"fIIL/V26XBpNr4FaQd5xO7SWZVIB/qq6VTBoumFxXk8="},"senderSigningKey":{"public":"BY+uKtN0XxhHNGBwbM/FcDSksG/aab15yMPr3xvr86Rl"},"senderMessageKeys":[]},{"senderKeyId":119979188,"senderChainKey":{"iteration":7,"seed":"iNXbBKfRifXB423skwhrchNmiz96H8KJ+8y+kjlJpc8="},"senderSigningKey":{"public":"BY+uKtN0XxhHNGBwbM/FcDSksG/aab15yMPr3xvr86Rl"},"senderMessageKeys":[]},{"senderKeyId":119979188,"senderChainKey":{"iteration":193,"seed":"G2642y/Ut+gjmQ43+xdWpir+AqTR8nqlROerzMXA38s="},"senderSigningKey":{"public":"BY+uKtN0XxhHNGBwbM/FcDSksG/aab15yMPr3xvr86Rl"},"senderMessageKeys":[]},{"senderKeyId":119979188,"senderChainKey":{"iteration":197,"seed":"Cl7wBW4xhdg4RAvuuCh/stv2Pu//ZzcarUy2sdjH00M="},"senderSigningKey":{"public":"BY+uKtN0XxhHNGBwbM/FcDSksG/aab15yMPr3xvr86Rl"},"senderMessageKeys":[]}]